LICENSE
README.rst
setup.py
shapelet_space/__init__.py
shapelet_space/dtw.py
shapelet_space/shapelet.py
shapelet_space.egg-info/PKG-INFO
shapelet_space.egg-info/SOURCES.txt
shapelet_space.egg-info/dependency_links.txt
shapelet_space.egg-info/requires.txt
shapelet_space.egg-info/top_level.txt