Metadata-Version: 2.1
Name: shapelet-space
Version: 0.1.1
Author: Somyadeep Shrivastava
License-File: LICENSE
Requires-Dist: pandas
Requires-Dist: numpy
Requires-Dist: scipy
